rcnnmasks
