Metadata-Version: 1.2
Name: rcnnmasks
Version: 0.0.6
Summary: Mask R-CNN for object detection and instance segmentation
Home-page: UNKNOWN
Author: Alexandra
Author-email: aleksandra.anna.pestka@gmail.com
License: MIT
Keywords: image instance segmentation object detection mask rcnn r-cnn tensorflow keras
Platform: UNKNOWN
Classifier: Development Status :: 5 - Production/Stable
Classifier: Environment :: Console
Classifier: Intended Audience :: Developers
Classifier: Intended Audience :: Information Technology
Classifier: Intended Audience :: Education
Classifier: Intended Audience :: Science/Research
Classifier: License :: OSI Approved :: MIT License
Classifier: Natural Language :: English
Classifier: Operating System :: OS Independent
Classifier: Topic :: Scientific/Engineering :: Artificial Intelligence
Classifier: Topic :: Scientific/Engineering :: Image Recognition
Classifier: Topic :: Scientific/Engineering :: Visualization
Classifier: Programming Language :: Python :: 3.4
Classifier: Programming Language :: Python :: 3.5
Classifier: Programming Language :: Python :: 3.6
Requires-Python: >=3.4
